{
  "$schema": "https://ui.shadcn.com/schema/registry-item.json",
  "name": "comp-396",
  "type": "registry:component",
  "dependencies": [
    "@radix-ui/react-avatar",
    "react",
    "clsx",
    "tailwind-merge"
  ],
  "files": [
    {
      "type": "registry:component",
      "target": "components/originui/comp-396.tsx",
      "content": "import { Avatar, AvatarFallback, AvatarImage } from \"@/components/ui/avatar\";\n\nexport default function Component() {\n  return (\n    <div className=\"relative\">\n      <Avatar className=\"rounded-md\">\n        <AvatarImage src=\"./avatar-80-07.jpg\" alt=\"Kelly King\" />\n        <AvatarFallback>KK</AvatarFallback>\n      </Avatar>\n      <span className=\"border-background absolute -end-1 -top-1 size-3 rounded-full border-2 bg-emerald-500\">\n        <span className=\"sr-only\">Online</span>\n      </span>\n    </div>\n  );\n}\n",
      "path": "registry/default/components/comp-396.tsx"
    },
    {
      "type": "registry:ui",
      "target": "components/ui/avatar.tsx",
      "content": "\"use client\";\n\nimport * as AvatarPrimitive from \"@radix-ui/react-avatar\";\nimport * as React from \"react\";\n\nimport { cn } from \"@/lib/utils\";\n\nfunction Avatar({ className, ...props }: React.ComponentProps<typeof AvatarPrimitive.Root>) {\n  return (\n    <AvatarPrimitive.Root\n      data-slot=\"avatar\"\n      className={cn(\"relative flex size-8 shrink-0 overflow-hidden rounded-full\", className)}\n      {...props}\n    />\n  );\n}\n\nfunction AvatarImage({ className, ...props }: React.ComponentProps<typeof AvatarPrimitive.Image>) {\n  return (\n    <AvatarPrimitive.Image\n      data-slot=\"avatar-image\"\n      className={cn(\"aspect-square size-full\", className)}\n      {...props}\n    />\n  );\n}\n\nfunction AvatarFallback({\n  className,\n  ...props\n}: React.ComponentProps<typeof AvatarPrimitive.Fallback>) {\n  return (\n    <AvatarPrimitive.Fallback\n      data-slot=\"avatar-fallback\"\n      className={cn(\n        \"bg-secondary flex size-full items-center justify-center rounded-[inherit] text-xs\",\n        className,\n      )}\n      {...props}\n    />\n  );\n}\n\nexport { Avatar, AvatarFallback, AvatarImage };\n",
      "path": "registry/default/ui/avatar.tsx"
    },
    {
      "type": "registry:lib",
      "target": "lib/utils.ts",
      "content": "import { clsx, type ClassValue } from \"clsx\";\nimport { twMerge } from \"tailwind-merge\";\n\nexport function cn(...inputs: ClassValue[]) {\n  return twMerge(clsx(inputs));\n}\n",
      "path": "registry/default/lib/utils.ts"
    }
  ],
  "meta": {
    "tags": [
      "avatar",
      "user",
      "profile",
      "status"
    ],
    "style": 1
  }
}
