{
  "$schema": "https://ui.shadcn.com/schema/registry-item.json",
  "name": "comp-547",
  "type": "registry:component",
  "files": [
    {
      "path": "registry/default/components/comp-547.tsx",
      "content": "\"use client\"\n\nimport type React from \"react\"\nimport { AlertCircleIcon, ImageIcon, UploadIcon, XIcon } from \"lucide-react\"\n\nimport {\n  formatBytes,\n  useFileUpload,\n} from \"@/registry/default/hooks/use-file-upload\"\nimport { Button } from \"@/registry/default/ui/button\"\n\nconst initialFiles = [\n  {\n    name: \"image-01.jpg\",\n    size: 1528737,\n    type: \"image/jpeg\",\n    url: \"https://picsum.photos/1000/800?grayscale&random=1\",\n    id: \"image-01-123456789\",\n  },\n  {\n    name: \"image-02.jpg\",\n    size: 2345678,\n    type: \"image/jpeg\",\n    url: \"https://picsum.photos/1000/800?grayscale&random=2\",\n    id: \"image-02-123456789\",\n  },\n  {\n    name: \"image-03.jpg\",\n    size: 3456789,\n    type: \"image/jpeg\",\n    url: \"https://picsum.photos/1000/800?grayscale&random=3\",\n    id: \"image-03-123456789\",\n  },\n]\n\nexport default function Component() {\n  const maxSizeMB = 5\n  const maxSize = maxSizeMB * 1024 * 1024 // 5MB default\n  const maxFiles = 6\n\n  const [\n    { files, isDragging, errors },\n    {\n      handleDragEnter,\n      handleDragLeave,\n      handleDragOver,\n      handleDrop,\n      openFileDialog,\n      removeFile,\n      clearFiles,\n      getInputProps,\n    },\n  ] = useFileUpload({\n    accept: \"image/svg+xml,image/png,image/jpeg,image/jpg,image/gif\",\n    maxSize,\n    multiple: true,\n    maxFiles,\n    initialFiles,\n  })\n\n  return (\n    <div className=\"flex flex-col gap-2\">\n      {/* Drop area */}\n      <div\n        onDragEnter={handleDragEnter}\n        onDragLeave={handleDragLeave}\n        onDragOver={handleDragOver}\n        onDrop={handleDrop}\n        data-dragging={isDragging || undefined}\n        data-files={files.length > 0 || undefined}\n        className=\"border-input data-[dragging=true]:bg-accent/50 has-[input:focus]:border-ring has-[input:focus]:ring-ring/50 relative flex min-h-52 flex-col items-center overflow-hidden rounded-xl border border-dashed p-4 transition-colors not-data-[files]:justify-center has-[input:focus]:ring-[3px]\"\n      >\n        <input {...getInputProps()} aria-label=\"Upload image file\" />\n        <div className=\"flex flex-col items-center justify-center px-4 py-3 text-center\">\n          <div\n            className=\"bg-background mb-2 flex size-11 shrink-0 items-center justify-center rounded-full border\"\n            aria-hidden=\"true\"\n          >\n            <ImageIcon className=\"size-4 opacity-60\" />\n          </div>\n          <p className=\"mb-1.5 text-sm font-medium\">Drop your images here</p>\n          <p className=\"text-muted-foreground text-xs\">\n            SVG, PNG, JPG or GIF (max. {maxSizeMB}MB)\n          </p>\n          <Button variant=\"outline\" className=\"mt-4\" onClick={openFileDialog}>\n            <UploadIcon className=\"-ms-1 opacity-60\" aria-hidden=\"true\" />\n            Select images\n          </Button>\n        </div>\n      </div>\n\n      {errors.length > 0 && (\n        <div\n          className=\"text-destructive flex items-center gap-1 text-xs\"\n          role=\"alert\"\n        >\n          <AlertCircleIcon className=\"size-3 shrink-0\" />\n          <span>{errors[0]}</span>\n        </div>\n      )}\n\n      {/* File list */}\n      {files.length > 0 && (\n        <div className=\"space-y-2\">\n          {files.map((file) => (\n            <div\n              key={file.id}\n              className=\"bg-background flex items-center justify-between gap-2 rounded-lg border p-2 pe-3\"\n            >\n              <div className=\"flex items-center gap-3 overflow-hidden\">\n                <div className=\"bg-accent aspect-square shrink-0 rounded\">\n                  <img\n                    src={file.preview}\n                    alt={file.file.name}\n                    className=\"size-10 rounded-[inherit] object-cover\"\n                  />\n                </div>\n                <div className=\"flex min-w-0 flex-col gap-0.5\">\n                  <p className=\"truncate text-[13px] font-medium\">\n                    {file.file.name}\n                  </p>\n                  <p className=\"text-muted-foreground text-xs\">\n                    {formatBytes(file.file.size)}\n                  </p>\n                </div>\n              </div>\n\n              <Button\n                size=\"icon\"\n                variant=\"ghost\"\n                className=\"text-muted-foreground/80 hover:text-foreground -me-2 size-8 hover:bg-transparent\"\n                onClick={() => removeFile(file.id)}\n                aria-label=\"Remove file\"\n              >\n                <XIcon aria-hidden=\"true\" />\n              </Button>\n            </div>\n          ))}\n\n          {/* Remove all files button */}\n          {files.length > 1 && (\n            <div>\n              <Button size=\"sm\" variant=\"outline\" onClick={clearFiles}>\n                Remove all files\n              </Button>\n            </div>\n          )}\n        </div>\n      )}\n\n      <p\n        aria-live=\"polite\"\n        role=\"region\"\n        className=\"text-muted-foreground mt-2 text-center text-xs\"\n      >\n        Multiple image uploader w/ image list\n      </p>\n    </div>\n  )\n}\n",
      "type": "registry:component"
    }
  ],
  "meta": {
    "tags": [
      "upload",
      "file"
    ],
    "colSpan": 2
  }
}